testpackage1290/__init__.py
testpackage1290/math.py
testpackage1290-0.0.3.dist-info/LICENSE
testpackage1290-0.0.3.dist-info/METADATA
testpackage1290-0.0.3.dist-info/WHEEL
testpackage1290-0.0.3.dist-info/top_level.txt
testpackage1290-0.0.3.dist-info/RECORD
