Metadata-Version: 2.1
Name: testpackage1290
Version: 0.0.3
Summary: A simple example package
Home-page: https://pypi.org/project/testpackage1290/
Author: Stefan Jansen
Author-email: stefanjansen95@hotmail.com
License: MIT
Classifier: Programming Language :: Python :: 3
Classifier: License :: OSI Approved :: MIT License
Classifier: Operating System :: OS Independent
Requires-Python: >=3.6
License-File: LICENSE
